HISTORY.rst
LICENSE
MANIFEST.in
README.rst
__about__.py
flask_language.py
setup.py
Flask_Language.egg-info/PKG-INFO
Flask_Language.egg-info/SOURCES.txt
Flask_Language.egg-info/dependency_links.txt
Flask_Language.egg-info/not-zip-safe
Flask_Language.egg-info/requires.txt
Flask_Language.egg-info/top_level.txt
docs/Makefile
docs/conf.py
docs/index.rst
docs/make.bat
tests/__init__.py
tests/test_language.py